Workbook

Sheet Cover
A1: Income Expense Forecast
A25: Your Personal Finance Organizer

Sheet April 2026 - June 2026
A1: Income Expense For the Forecast Year 2026 April - June 2026
A3: Assets | B3: Banks ~ HSBC Bank ~ Bank Of China ~ Standard Chartered Bank | C3: 41.51
B4: Coins And Cash | C4: 724.7
B5: Unit Trusts ~ AIA Insurance ~ MPF | C5: 0
B6: Alipay HK | C6: 0
B7: Paypal | C7: 9
B8: Octopus Remain Value | C8: 31.7
B9: Total Asset | C9: =SUM(C3:C8) -> 806.91
A11: April 20th - May 19th 2026 Revenue / Defered Debts Or Expenses
A12: Date | B12: Name | C12: Description | E12: Amount
A13: 20th April 2026 | B13: Social Welfare | C13: Disability Allowance | E13: 2485
A14: 20th April 2026 | B14: Communication | C14: China Mobile | E14: 12
B15: e-cigarette | C15: Already Brought E-cigarette on March enough for this month | E15: 900
B16: Optifast plus | C16: Sell it | E16: 1050
B17: Loan | C17: Borrow from Lawrence | E17: 700
A18: 46138 | B18: Mother | C18: 1. Return back From Mom HKT Fixed Line Services - $140 2. Remaining Mother Credit Card to puchase from Amazon - $7.6 3. Borrow $40 | E18: 187.6
B19: Communication | C19: Netflix Not Yet Registered | E19: 118
A20: 21st April 2026 | B20: Octopus | C20: Topup $50 For Octopus | E20: 50
D21: Forecast Total | E21: =SUM(E13:E20) -> 5502.6
A23: May 20th - June 17th 2026 Revenue / Defered Debts Or Expenses
A24: Date | B24: Name | C24: Description | E24: Amount
A25: 20th May 2026 | B25: Social Welfare | C25: Disability Allowance | E25: 2485
A26: Early June 2026 | B26: Social Welfare | C26: Additional One Month Disability Allowance | E26: 2140
B27: Mother | C27: 1. 20th May 2026 - Give back the Water Fees paid for the government. - $112.3 2. 23rd May 2026 - Mother payback for the shopping. - $100 3. 17th June 2026 - Mother payback for the OK Store - $15 | E27: 227.3
A28: 20th May 2026 | B28: e-cigarette | C28: Buy 5 give 1 discount for $695 original $900 | E28: 205
B29: Octopus | C29: 1. Topup For Octopus Card (Credit $50). 2. Topup For Octopus Card (Credit $50) on 23/05. 3. Topup For Octopus Card (Credit $50) on 01/06. | E29: 150
D30: Forecast Total | E30: =SUM(E25:E29) -> 5207.3
A32: June 18th - August 19th 2026 Revenue / Defered Debts Or Expenses
A33: Date | B33: Name | C33: Description | E33: Amount
A34: 20th June 2026 | B34: Social Welfare | C34: Disability Allowance | E34: 2485
B35: Communication | C35: Cancel Netflix | E35: 118
B36: Mother | C36: 1. Payback For Clothes Washing Detergent. 2. Borrow $100 from Mom. | E36: 170
B37: Lawrence | C37: 1. $300 Rent my Luggage. 2. Borrow $500 from Lawrece. | E37: 800
B38: Octopus | C38: 1. Topup For Octopus Card (Credit $100). 2. Topup For Octopus Card (Credit $100) 19/07. | E38: 200
D39: Forecast Total | E39: =SUM(E34:E38) -> 3773
A41: Fixed Expense For the Year 2026 April - June 2026
A42: Name | B42: Description | C42: Amount
A43: Mobile And Communications
A44: China Mobile | B44: Broadband | C44: 78
A45: Netflix | B45: Premium | C45: 118
A46: China Mobile | B46: 5G Plan | C46: 138
B47: Total Payment | C47: =SUM(C44:C46) -> 334
A48: Credit Card Installments/Expense
A50: Citi Bank | C50: 0
A51: SC Bank - Smart | C51: 0
A52: Bank Of China | C52: 0
A53: HSBC Red | C53: 0
B54: Total Installments | C54: =SUM(C50:C53) -> 0
A55: Donation
A56: Traverse Media | B56: Youtube Javascript Channel | C56: 0
A57: Orbis | B57: Orbis Eye Flight | C57: 0
B58: Total Donation | C58: =SUM(C56:C57) -> 0
A59: Insurance
A60: AIA | B60: AIA Insurance | C60: 0
B61: Total Insurance | C61: =SUM(C60) -> 0
A62: House Expense
A63: Salary | B63: Mom | C63: 0
B64: Total House Expense | C64: =SUM(C63) -> 0
A65: Other Expense
A66: Other Stuff | B66: Food, Transport…. | C66: 0
A67: Cigarettes | B67: e-cigarette | C67: 900
A68: Weight Loss | B68: Optifast weight Loss Program (3 Months Program) | C68: 0
A69: Entertainment | B69: Sportify Music | C69: 78
A70: Hair Cut | C70: 55
A71: Visit Doctor | B71: Vist Psychology Doctor | C71: 0
B72: Total Other Expense | C72: =SUM(C66:C71) -> 1033
A73: Debts
A74: Mother | C74: 0
A75: Lawrence | C75: 0
B76: Total Debts | C76: =SUM(C74:C75) -> 0
B77: Monthly Total | C77: =C47+C54+C58+C61+C64+C72 -> 1367
A80: Debts Or Expenses For the Comming April 20th - May 19th 2026
A81: Principal | C81: Description | E81: Amount
A82: Blance Brought Forward | E82: 21.98
A83: Other Expense | C83: MAGGI Orginal Mashed Potato with Beef 12x35g * 2 | E83: 168
C84: ~ U-store - $82.4 ~ U-store Ovaltine malted milk $25 ~ OK Store - $63.6 ~ Wellcome supermarket $49.5 ~ U-store 26/04 - $34.9 ~ Best Mart 360 26/04 - $25 ~ OK Store 27/04 - $23 ~ St Honer 27/04 - $31 ~ OK Store 03/05 - $29.5 ~ Best Mart 360 06/05 - $35 ~ OK Store 13/05 - $29.5 ~ OK Store 16/05 - $27.5 ~ A1 Bakery 17/05- $42 ~ U-store 18/05 - $9.8 | E84: 507.7
C85: ~ Optifast weight Loss Program | E85: 1728
C86: ~ Topup $50 For Octopus | E86: 50
C87: ~ Brought Classic Crocs - $418 | E87: 418
C88: ~ E-cigarette buds 6 packets plus delivery fees | E88: 697
C89: ~ Transportation To Prince Edward ~ Transportation To Hospital | E89: 5.4
C90: ~ Pay HKT Fixed Telephone Line Services 2 months - $136 | E90: 136
C91: ~ Pay Water Fees | E91: 112.3
C92: ~ Amazon clairol hair bleaching plus insoles - $366.38 | E92: 366.38
A93: Fixed Expense | E93: =C77 -> 1367
C94: Total Debts / Credits | E94: =(E21+E82)-SUM(E83:E93) -> -31.2
A96: Debts Or Expenses For the Coming May 20th - June 17th 2026
A97: Principal | C97: Description | E97: Amount
A98: Balance Brought Forward From April 2026 | E98: =E94 -> -31.2
A99: Other Expense | C99: ~ Payback to Lawrence (postpone to additional one month allowance for paying back) ~ Payback to Mom | E99: 747.6
C100: ~ Food - $300 ($178.8) ~ Shopping on 23/05 - $121.4 ~ ParkNShop on 24/5 - $14 ~ Wellcome on 04/06 - $43.4 ~ Snacks And Drinks - $200 ($703.4) ~ Ovaltine Malt Drink 1 bottle - $25 ~ OK Store 23/05 - $26 ~ U-Store on 24/05 - $37.8 ~ Ovaltine Malt Drink 1 bottle on 26/05 - $25 ~ U-Store 26/05 - $55.8 ~ OK Store on 01/06 - $27.5 ~ OK Store on 03/06 - $25.5 ~ Ovaltine Malt Drink 1 bottle on 04/06 - $25 ~ UStore on 04/06 - $48.3 ~ DS Groceries 06/06 - $74 ~ UStore on 08/06 - $21.7 ~ UStore on 10/06 - $19.5 ~ UStore on 11/06 - $22.7 ~ DS Groceries 12/06 - $23 ~ Mitsui Bakery 12/06 - $18.5 ~ OK Store 13/06 - $35 ~ UStore on 14/06 - $35.3 ~ UStore on 15/06 - $9.8 ~ OK Store 16/06 - $33 ~ OK Store 17/06 - $26 ~ OK Store 17/06 - $107 | E100: 900.2
C101: ~ Buy additional Cigarette @ $81 each x 6 - $486 ~ Donate $100 to Chest Community - $100 ~ Pay Fees For HKT Fixed Line Phone - $68 ~ Mail Chuk Yuen Post Office - $2.4 | E101: 656.4
C102: ~ Debit For Octopus Card ($50). ~ Debit For Octopus Card ($50) on 23/05. ~ Debit For Octopus Card ($50) on 01/06. ~ Round Trip to Airport on 29/05 - $9.4 ~ Trip to Restaurant on 30/05 - $2 ~ Trip to Restaurant on 02/05 - $2 ~ Trip to East Kwoloon Hospital 08/06 - $4 | E102: 167.4
C103: ~ K-Swiss - $399 ~ Uniqlo Underware and Socks - $315 ~ Uniqlo T Shirt - $395 ~ UNISEX DRY COLOR CREW NECK T-SHIRT NAVY 4XL - $49 ~ MEN DRY V NECK T-SHIRT 484845 NAVY 4XL - $49 ~ UNISEX NY POP ART UT (SHORT SLEEVE GRAPHIC T-SHIRT) 485062 BLACK 3XL - $99 ~ UNISEX PEANUTS UT (SHORT SLEEVE GRAPHIC T-SHIRT) 485058 NATURAL 3XL - $99 ~ UNISEX MAGIC FOR ALL ICONS UT (SHORT SLEEVE GRAPHIC T-SHIRT) 484758 3XL - $99 | E103: 1109
A104: Fixed Expense | E104: =C77 -> 1367
C105: Total Debts / Credits | E105: =(E30+E98)-SUM(E99:E104) -> 228.5
A108: Debts Or Expenses For the Comming June 18th - July 19th 2026
A109: Principal | C109: Description | E109: Amount
A110: Balance Brought Forward From May 2026 | E110: =E105 -> 228.5
A111: Other Expense | C111: ~ Food - $300 (108.9) ~ ParkNShop 27/06 - $108.9 ~ Snack And Drinks - $400 ($761.4) ~ OK Store 18/06 - $67 ~ Chuk Yuen Store 18/06 - $4 ~ Best Mart 360 18/06 - $25 ~ Wellcome Supermarket 18/06 - $80.9 ~ Ustore 18/06 - $48.4 ~ Yummy Bread 18/06 - $16 ~ OK Store 21/06 - $30 ~ DS Groceries 22/06 - $55 ~ UStore 22/06 - $29.6 ~ UStore 26/06 - $95.7 ~ Ustore 28/06 - $31 ~ OK Store 01/07 - $24 ~ OK Store 05/07 - $113.1 ~ OK Store 07/07 - $43.1 ~ OK Store 11/07 - $18 ~ Ustore 14/07 - $55.6 ~ Best Mart 360 16/07 - $25 | E111: 870.3
...

Sheet July 2026- September 2026
A1: Income Expense For the Forecast Year 2026 July - September 2026
A3: Assets | B3: Banks ~ HSBC Bank ~ Bank Of China ~ Standard Chartered Bank | C3: ='April 2026 - June 2026'!C3 -> 41.51
B4: Coins And Cash | C4: ='April 2026 - June 2026'!C4 -> 724.7
B5: Unit Trusts ~ AIA Insurance ~ MPF | C5: ='April 2026 - June 2026'!C5 -> 0
B6: Alipay HK | C6: ='April 2026 - June 2026'!C6 -> 0
B7: Paypal | C7: 9
B8: Octopus Remain Value | C8: ='April 2026 - June 2026'!C8 -> 31.7
B9: Total Asset | C9: ='April 2026 - June 2026'!C9 -> 806.91
A11: July 20th - August 19th 2026 Revenue / Defered Debts Or Expenses
A12: Date | B12: Name | C12: Description | E12: Amount
A13: 20th July 2026 | B13: Social Welfare | C13: Disability Allowance | E13: 2485
A14: 21st July 2026 | B14: Hair Cut | C14: Cancel hair cut for this current month. | E14: 55
A15: 06th Aug 2026 | B15: Mother | C15: 1. Borrow $100 2. Use Mother Credit Card for shopping HKTVmall. $670.4 | E15: 770.4
D16: Forecast Total | E16: =SUM(E13:E15) -> 3310.4
A18: August 20th - September 17th 2026 Revenue / Defered Debts Or Expenses
A19: Date | B19: Name | C19: Description | E19: Amount
A20: 20th August 2026 | B20: Social Welfare | C20: Disability Allowance | E20: 2485
A21: 20th August 2026 | B21: Octopus | C21: 1. Top up $50 for Octopus 2. Top up $50 for Octopus 03/09 | E21: 100
A22: 23rd August 2026 | B22: Alipay | C22: A discount of $3.08 for iHerb payment | E22: 3.08
A23: 2nd September 2026 | B23: Mother | C23: 1. Borrow $60 2. Payback Water bill through Alipay $74.1. 3. Borrow $100 ~ 16/09 | E23: 234.1
A24: 3rd September 2026 | B24: Brother | C24: 1. A gift for birthday $1000 from Lawrence 2. Borrow $500 | E24: 1500
D25: Forecast Total | E25: =SUM(E20:E24) -> 4322.18
A27: September 18th - October 19th 2026 Revenue / Defered Debts Or Expenses
A28: Date | B28: Name | C28: Description | E28: Amount
A29: 18th September 2026 | B29: Social Welfare | C29: Disability Allowance | E29: 2485
A30: 18th September 2026 | B30: Octopus | C30: 1. Top up $50 for Octopus 18/09 2. Top up $50 for Octopus 18/09 3. Top up $50 for Octopus 26/09 | E30: 150
A31: 21st September 2026 | B31: Mother | C31: 1. A gift for birthday $500 from Mother. 2. Refund from "GoDaddy domain" to moms credit card account. 27/09/2025 - $193.98 3. Refund from "GoDaddy domain" to moms credit card account. 29/09/2025 - $721.86 | E31: 1415.84
D32: Forecast Total | E32: =SUM(E29:E31) -> 4050.84
A34: Fixed Expense For the Year 2026 July - September 2026
A35: Name | B35: Description | C35: Amount
A36: Mobile And Communications
A37: China Mobile | B37: Broadband | C37: 78
A38: Netflix | B38: Premium | C38: 0
A39: China Mobile | B39: 5G Plan | C39: 138
B40: Total Payment | C40: =SUM(C37:C39) -> 216
A41: Credit Card Installments/Expense
A43: Citi Bank | C43: 0
A44: SC Bank - Smart | C44: 0
A45: Bank Of China | C45: 0
A46: HSBC Red | C46: 0
B47: Total Installments | C47: =SUM(C43:C46) -> 0
A48: Donation
A49: Traverse Media | B49: Youtube Javascript Channel | C49: 0
A50: Orbis | B50: Orbis Eye Flight | C50: 0
B51: Total Donation | C51: =SUM(C49:C50) -> 0
A52: Insurance
A53: AIA | B53: AIA Insurance | C53: 0
B54: Total Insurance | C54: =SUM(C53) -> 0
A55: House Expense
A56: Salary | B56: Mom | C56: 0
B57: Total House Expense | C57: =SUM(C56) -> 0
A58: Other Expense
A59: Other Stuff | B59: Food, Transport…. | C59: 0
A60: Cigarettes | B60: e-cigarette | C60: 900
A61: Weight Loss | B61: Optifast weight Loss Program (3 Months Program) | C61: 0
A62: Entertainment | B62: Sportify Music | C62: 0
A63: Hair Cut | C63: 55
A64: Visit Doctor | B64: Vist Psychology Doctor | C64: 0
B65: Total Other Expense | C65: =SUM(C59:C64) -> 955
A66: Debts
A67: Mother | C67: 0
A68: Lawrence | C68: 0
B69: Total Debts | C69: =SUM(C67:C68) -> 0
B70: Monthly Total | C70: =C40+C47+C51+C54+C57+C65 -> 1171
A73: Debts Or Expenses For the Comming July 20th - August 19th 2026
A74: Principal | C74: Description | E74: Amount
A75: Blance Brough Forward From June 2026 | E75: ='April 2026 - June 2026'!E115 -> 110.7
A76: Other Expense | C76: ~ Payback $500 to Lawrence ~ Payback $100 to Mom | E76: 600
C77: ~ Food ~ Snack And Drinks ~ Ok Store 20/07 - $15 ~ Ok Store 21/07 - $28.4 ~ Wellcome supermarket 21/07 - $138.4 ~ Yummy Bread Store 21/07 - $13 ~ Wellcome supermarket 22/07 - $36 ~ Ustore 22/07 - $36.6 ~ Ok Store 25/07 - $32 ~ Wellcome supermarket 25/07 - $36 ~ Ustore 27/07 - $24.9 ~ OK Store 29/07 - $28.5 ~ Buy a coke at Kwai Chung Eldery Hospital 05/08 - $6.5 ~ Best Mart 360 05/08 - $26.9 ~ Ustore 09/08 - $24.9 ~ HKTVmall 18/08 - $670.4 | E77: 1117.5
C78: ~ OK Store buy additional 1 packet cigarette 20/07 - $78 ~ Additional transport fees for e-cigarette 20/07 - $40 ~ HKTVmall - Microsoft Office 365 1 year subscribtion 30/07 - $299 ~ Round Trip to Kowloon East Hospital 03/08 - $4 ~ Round Trip to Kwai Chung Eldery Hospital 05/08 - $3.5 ~ Round Trip to Kwai Chung Eldery Hospital 16/08 - $3.5 ~ OK Store buy additional 1 packet cigarette 18/08 - $78 ~ Single Trip from chuk yuen to Temple Mall 19/08 - $2 | E78: 508
A79: Fixed Expense | E79: =C70 -> 1171
C80: Total Debts / Credits | E80: =(E16+E75)-SUM(E76:E79) -> 24.6
A82: Debts Or Expenses For the Coming August 20th - September 17th 2026
A83: Principal | C83: Description | E83: Amount
A84: Balance Brought Forward From July 2026 | E84: =E80 -> 24.6
A85: Other Expense | C85: ~ Payback $100 to Mom ~ Payback $670.4 to Mom (HKTVmall Online Shopping) ~ Payback $60 to Mom | E85: 830.4
C86: Partial Food And Snack Prepaid on the Previous Month ~ Food ~ HKTV mall 24/08 - $211.4 ~ HKTV mall 03/09 - $436.5 ~ Snack And Drinks ~ OK Store 20/08 - $8.5 ~ Ustore 03/09 - $55.2 ~ Ustore 05/09 - $9.8 | E86: 721.4
C87: ~ Debit For Octopus Card ($50). 20/08 ~ OK Store buy additional 1 packet cigarette 20/08 - $78 ~ Mail Chuk Yuen Post Office - $2.4 ~ Additional transport fees for e-cigarette 20/08 - $50 ~ Paid Water Supplies Fees 20/08 - $74.1 ~ Round Trip to East Kowloon hospital 31/08 - $4 ~ Round Trip to East Kowloon hospital 03/09 - $4 ~ Debit For Octopus Card ($50). 03/09 ~ OK Store buy additional 1 packet cigarette 11/09 - $78 ~ OK Store buy additional 1 packet cigarette 12/09 - $78 ~ OK Store buy additional 1 packet cigarette 13/09 - $78 ~ OK Store buy additional 3 packet cigarette 14/09 - $234 ~ OK Store buy additional 2 packet cigarette 16/09 - $156 ~ OK Store 16/09 - $20 | E87: 956.5
C88: ~ iHerb Aveeno Lotion 23/08 - $136.64 ~ Watsons Revlon color silk 17/09 - $59.9 | E88: 196.54
C89: ~ Uniqlo (buy $300 - $30 discount) - 03/09 ~ UNISEX EZY BARREL JEANS (INSEAM 72-78cm) 488630 / 492035 -$299 ~ UNISEX ULTRA STRETCH ACTIVE SHORTS (INSEAM 18-21.5cm) 482317 - $99 ~ MEN COTTON BOXER BRIEFS 482600- $29 x 2 | E89: 426
A90: Fixed Expense | E90: =C70 -> 1171
C91: Total Debts / Credits | E91: =(E25+E84)-SUM(E85:E90) -> 44.94
A94: Debts Or Expenses For the Comming September 18th - October 19th 2026
A95: Principal | C95: Description | E95: Amount
A96: Balance Brought Forward From August 2026 | E96: =E91 -> 44.94
A97: Other Expense | C97: ~ Payback $250 to Lawrence ~ Payback $100 to Mom ~ Payback $250 to Lawrence | E97: 600
C98: Partial Food And Snack Prepaid on the Previous Month ~ Food ~ HKTV mall 18/09 - $339.9 ~ Ustore 02/10 - $104.3 ~ Snack And Drinks ~ 7 Eleven 18/09 - $12 ~ Ustore 02/10 - $30 ~ OK store 07/10 - $61.5 ~ OK Store 08/10 - $22 ~ BestMart 360 08/10 - $39 ~ OK Store 09/10 - $20 ~ OK Store 11/10 - $20 ~ OK Store 12/10 - $22 ~ OK Store 14/10 - $22 ~ OK Store 16/10 - $22 | E98: 714.7
C99: ~ Additional fees for cigarette (change from e-cigarette to cigarette) 18/09 - $380 ~ OK Store buy additional 1 packet cigarette 18/09 - $78 ~ Debit For Octopus Card ($50). 18/09 ~ Debit For Octopus Card ($50). 18/09 ~ OK Store buy additional 1 packet cigarette 18/09 - $78 ~ OK Store buy additional 1 packet cigarette 19/09 - $78 ~ Debit For Octopus Card ($50). 26/09 ~ Round Trip to East Kowloon hospital 02/10 - $4 ~ Buy 2 packs of cigarette (each packs contains 10 packets) 09/10 - $640 ~ OK Store buy lighter 11/10 - $11 | E99: 1419
C100: ~ iHerb Aveeno Lotion - $136.64 ~ Carousell Revlon color silk 12/10 - $54.72 | E100: 191.36
A101: Fixed Expense | E101: =C70 -> 1171
C102: Total Debts / Credits | E102: =(E32+E96)-SUM(E97:E101) -> -0.28

Sheet October 2026- December 2026
A1: Income Expense For the Forecast Year 2026 October - December 2026
A3: Assets | B3: Banks ~ HSBC Bank ~ Bank Of China ~ Standard Chartered Bank | C3: ='April 2026 - June 2026'!C3 -> 41.51
B4: Coins And Cash | C4: ='April 2026 - June 2026'!C4 -> 724.7
B5: Unit Trusts ~ AIA Insurance ~ MPF | C5: ='April 2026 - June 2026'!C5 -> 0
B6: Alipay HK | C6: ='April 2026 - June 2026'!C6 -> 0
B7: Paypal | C7: 9
B8: Octopus Remain Value | C8: ='April 2026 - June 2026'!C8 -> 31.7
B9: Total Asset | C9: ='April 2026 - June 2026'!C9 -> 806.91
A11: October 20th - November 19th 2026 Revenue / Defered Debts Or Expenses
A12: Date | B12: Name | C12: Description | E12: Amount
A13: 20th October 2026 | B13: Social Welfare | C13: Disability Allowance | E13: 2485
A14: 20th October 2026 | C14: 1. Cancel hair cut. | E14: 55
A15: 20th October 2026 | B15: Mother | C15: 1. Payback $136 for the fixed line fees | E15: 136
A16: 20th October 2026 | B16: Octopus | C16: 1. Top up $100 for Octopus | E16: 100
A17: 20th October 2026 | B17: Carousel | C17: Cancel carousel order for dyeing | E17: 54.72
D18: Forecast Total | E18: =SUM(E13:E17) -> 2830.72
A20: November 20th - December 17th 2026 Revenue / Defered Debts Or Expenses
A21: Date | B21: Name | C21: Description | E21: Amount
A22: 20th November 2026 | B22: Social Welfare | C22: Disability Allowance | E22: 2485
E23: 0
D24: Forecast Total | E24: =SUM(E22:E23) -> 2485
A26: December 18th - January 19th 2027 Revenue / Defered Debts Or Expenses
A27: Date | B27: Name | C27: Description | E27: Amount
A28: 18th December 2026 | B28: Social Welfare | C28: Disability Allowance | E28: 2485
E29: 0
D30: Forecast Total | E30: =SUM(E28:E29) -> 2485
A32: Fixed Expense For the Year 2026 October - December 2026
A33: Name | B33: Description | C33: Amount
A34: Mobile And Communications
A35: China Mobile | B35: Broadband | C35: 78
A36: Netflix | B36: Premium | C36: 0
A37: China Mobile | B37: 5G Plan | C37: 138
B38: Total Payment | C38: =SUM(C35:C37) -> 216
A39: Credit Card Installments/Expense
A41: Citi Bank | C41: 0
A42: SC Bank - Smart | C42: 0
A43: Bank Of China | C43: 0
A44: HSBC Red | C44: 0
B45: Total Installments | C45: =SUM(C41:C44) -> 0
A46: Donation
A47: Traverse Media | B47: Youtube Javascript Channel | C47: 0
A48: Orbis | B48: Orbis Eye Flight | C48: 0
B49: Total Donation | C49: =SUM(C47:C48) -> 0
A50: Insurance
A51: AIA | B51: AIA Insurance | C51: 0
B52: Total Insurance | C52: =SUM(C51) -> 0
A53: House Expense
A54: Salary | B54: Mom | C54: 0
B55: Total House Expense | C55: =SUM(C54) -> 0
A56: Other Expense
A57: Other Stuff | B57: Food, Transport…. | C57: 0
A58: Cigarettes | B58: cigarette - 4 packs each pack has 10 packets of cigarette | C58: 1280
A59: Weight Loss | B59: Optifast weight Loss Program (3 Months Program) | C59: 0
A60: Entertainment | B60: Sportify Music | C60: 0
A61: Hair Cut | C61: 55
A62: Visit Doctor | B62: Vist Psychology Doctor plus transport | C62: 0
B63: Total Other Expense | C63: =SUM(C57:C62) -> 1335
A64: Debts
A65: Mother | C65: 0
A66: Lawrence | C66: 0
B67: Total Debts | C67: =SUM(C65:C66) -> 0
B68: Monthly Total | C68: =C38+C45+C49+C52+C55+C63 -> 1551
A71: Debts Or Expenses For the Comming October 20th - November 19th 2026
A72: Principal | C72: Description | E72: Amount
A73: Blance Brough Forward From September 2026 | E73: ='July 2026- September 2026'!E102 -> -0.28
A74: Other Expense | E74: 0
C75: ~ Food ~ Snack And Drinks ~ OK Store $40 - 20/10 ~ Best Mart 360 20/10 - $22.9 ~ Wellcome 20/10 - $112 ~ Ustore 23/10 - $97 ~ Best Mart 360 23/10 - $25 ~ OK Store 25/10 - $63 ~ OK Store 27/10 - $26 ~ OK Store - $25 (Octopus paid-need to confirm) ~ Best Mart 360 30/10 - $25 | E75: 435.9
C76: ~ Debit For Octopus Card ($100). 20/10 ~ Help mom to paid the fixline fees $136 - 20/10 ~ Gandi domain name programming.website renewal $312.73 - 26/10 ~ HSBC Global Transfer Charges $70 - 26/10 ~ Round Trip to Kowloon East Hospital 30/10 - $4 | E76: 622.73
C77: ~ Revlon color stay 20/10 - $53.9 | E77: 53.9
A78: Fixed Expense | E78: =C68 -> 1551
C79: Total Debts / Credits | E79: =(E18+E73)-SUM(E74:E78) -> 166.91
A81: Debts Or Expenses For the Coming November 20th - December 17th 2026
A82: Principal | C82: Description | E82: Amount
A83: Balance Brought Forward From October 2026 | E83: =E79 -> 166.91
A84: Other Expense | E84: 0
C85: ~ Food ~ Snack And Drinks | E85: 0
E86: 0
E87: 0
E88: 0
A89: Fixed Expense | E89: =C68 -> 1551
C90: Total Debts / Credits | E90: =(E24+E83)-SUM(E84:E89) -> 1100.91
A93: Debts Or Expenses For the Comming December 18th - January 19th 2027
A94: Principal | C94: Description | E94: Amount
A95: Balance Brought Forward From November 2026 | E95: =E90 -> 1100.91
A96: Other Expense | E96: 0
C97: ~ Food ~ Snack And Drinks | E97: 0
E98: 0
A99: Fixed Expense | E99: =C68 -> 1551
C100: Total Debts / Credits | E100: =(E30+E95)-SUM(E96:E99) -> 2034.91
